txfdjangomix/__init__.py
txfdjangomix/django_log/__init__.py
txfdjangomix/django_log/sql_log/__init__.py
txfdjangomix/django_log/sql_log/admin.py
txfdjangomix/django_log/sql_log/apps.py
txfdjangomix/django_log/sql_log/insert_django_sql.py
txfdjangomix/django_log/sql_log/models.py
txfdjangomix/django_log/sql_log/tests.py
txfdjangomix/django_log/sql_log/views.py
txfdjangomix/django_log/sql_log/migrations/__init__.py
txfdjangomix/django_response_middleware/__init__.py
txfdjangomix/django_response_middleware/django_response_middleware.py
txfdjangomix/django_response_middleware/response_codes.py
txfdjangomix/django_response_middleware/response_data.py
txfdjangomix/django_response_middleware/utils/__init__.py
txfdjangomix/django_response_middleware/utils/json_cls.py
txfdjangomix/django_response_middleware/utils/type_conversion.py
txfdjangomix/utils/__init__.py
txfdjangomix/utils/models.py
txfdjangomix-2.11.dist-info/LICENSE
txfdjangomix-2.11.dist-info/METADATA
txfdjangomix-2.11.dist-info/WHEEL
txfdjangomix-2.11.dist-info/top_level.txt
txfdjangomix-2.11.dist-info/zip-safe
txfdjangomix-2.11.dist-info/RECORD
