Metadata-Version: 2.1
Name: txfdjangomix
Version: 2.11
Summary: django response middleware
Home-page: https://github.com/txf402066270/txfdjangomix/
Author: wu-di-tian-ge-ge
Author-email: 402066270@qq.com
License: NEU
Classifier: Programming Language :: Python
Classifier: Intended Audience :: Developers
Classifier: Operating System :: OS Independent
License-File: LICENSE
Requires-Dist: django
Requires-Dist: djangorestframework
